axial/__init__.py
axial/axial.py
axial/go/__init__.py
axial/go/human_gene_sets.js
axial/go/mouse_gene_sets.js
axial/templates/__init__.py
axial/templates/bar.html.j2
axial/templates/base.html.j2
axial/templates/braid.html.j2
axial/templates/graph.html.j2
axial/templates/heatmap.html.j2
axial/templates/volcano.html.j2
axial-0.2.3.dist-info/LICENSE
axial-0.2.3.dist-info/METADATA
axial-0.2.3.dist-info/WHEEL
axial-0.2.3.dist-info/top_level.txt
axial-0.2.3.dist-info/RECORD
